vspec/__init__.py
vspec/loggingconfig.py
vspec/py.typed
vspec/vspec2vss_config.py
vspec/vspec2x.py
vspec/vss2x.py
vspec/model/__init__.py
vspec/model/constants.py
vspec/model/exceptions.py
vspec/model/vsstree.py
vspec/utils/__init__.py
vspec/utils/idgen_utils.py
vspec/utils/stringstyle.py
vspec/utils/vss2id_val.py
vspec/vssexporters/__init__.py
vspec/vssexporters/vss2binary.py
vspec/vssexporters/vss2csv.py
vspec/vssexporters/vss2ddsidl.py
vspec/vssexporters/vss2franca.py
vspec/vssexporters/vss2graphql.py
vspec/vssexporters/vss2id.py
vspec/vssexporters/vss2json.py
vspec/vssexporters/vss2jsonschema.py
vspec/vssexporters/vss2protobuf.py
vspec/vssexporters/vss2yaml.py
vss_tools-4.2.data/scripts/vspec2csv.py
vss_tools-4.2.data/scripts/vspec2ddsidl.py
vss_tools-4.2.data/scripts/vspec2franca.py
vss_tools-4.2.data/scripts/vspec2graphql.py
vss_tools-4.2.data/scripts/vspec2id.py
vss_tools-4.2.data/scripts/vspec2json.py
vss_tools-4.2.data/scripts/vspec2jsonschema.py
vss_tools-4.2.data/scripts/vspec2protobuf.py
vss_tools-4.2.data/scripts/vspec2yaml.py
vss_tools-4.2.dist-info/LICENSE
vss_tools-4.2.dist-info/METADATA
vss_tools-4.2.dist-info/WHEEL
vss_tools-4.2.dist-info/top_level.txt
vss_tools-4.2.dist-info/RECORD
