Metadata-Version: 2.1
Name: vss-tools
Version: 4.2
Summary: COVESA Vehicle Signal Specification tooling.
Home-page: https://github.com/COVESA/vss-tools
License: Mozilla Public License 2.0
Requires-Python: >=3.8
License-File: LICENSE
Requires-Dist: pyyaml >=5.1
Requires-Dist: anytree >=2.8.0
Requires-Dist: deprecation >=2.1.0
Requires-Dist: graphql-core
Requires-Dist: importlib-metadata >=7.0
